odoo/addons/stock_vertical_lift/README.rst
odoo/addons/stock_vertical_lift/__init__.py
odoo/addons/stock_vertical_lift/__manifest__.py
odoo/addons/stock_vertical_lift/controllers/__init__.py
odoo/addons/stock_vertical_lift/controllers/main.py
odoo/addons/stock_vertical_lift/data/ir_sequence.xml
odoo/addons/stock_vertical_lift/demo/product_demo.xml
odoo/addons/stock_vertical_lift/demo/stock_location_demo.xml
odoo/addons/stock_vertical_lift/demo/stock_picking_demo.xml
odoo/addons/stock_vertical_lift/demo/stock_quant_demo.xml
odoo/addons/stock_vertical_lift/demo/vertical_lift_shuttle_demo.xml
odoo/addons/stock_vertical_lift/i18n/it.po
odoo/addons/stock_vertical_lift/i18n/stock_vertical_lift.pot
odoo/addons/stock_vertical_lift/images/O-BTN.release.svg
odoo/addons/stock_vertical_lift/images/O-BTN.save.svg
odoo/addons/stock_vertical_lift/images/O-BTN.skip.svg
odoo/addons/stock_vertical_lift/models/__init__.py
odoo/addons/stock_vertical_lift/models/res_config_settings.py
odoo/addons/stock_vertical_lift/models/stock_location.py
odoo/addons/stock_vertical_lift/models/stock_move.py
odoo/addons/stock_vertical_lift/models/stock_move_line.py
odoo/addons/stock_vertical_lift/models/stock_quant.py
odoo/addons/stock_vertical_lift/models/vertical_lift_command.py
odoo/addons/stock_vertical_lift/models/vertical_lift_operation_base.py
odoo/addons/stock_vertical_lift/models/vertical_lift_operation_inventory.py
odoo/addons/stock_vertical_lift/models/vertical_lift_operation_pick.py
odoo/addons/stock_vertical_lift/models/vertical_lift_operation_put.py
odoo/addons/stock_vertical_lift/models/vertical_lift_shuttle.py
odoo/addons/stock_vertical_lift/readme/CONFIGURE.md
odoo/addons/stock_vertical_lift/readme/CONTRIBUTORS.md
odoo/addons/stock_vertical_lift/readme/CREDITS.md
odoo/addons/stock_vertical_lift/readme/DESCRIPTION.md
odoo/addons/stock_vertical_lift/readme/DEVELOP.md
odoo/addons/stock_vertical_lift/readme/ROADMAP.md
odoo/addons/stock_vertical_lift/security/ir.model.access.csv
odoo_addon_stock_vertical_lift-18.0.1.3.0.dist-info/METADATA
odoo_addon_stock_vertical_lift-18.0.1.3.0.dist-info/WHEEL
odoo_addon_stock_vertical_lift-18.0.1.3.0.dist-info/top_level.txt
odoo_addon_stock_vertical_lift-18.0.1.3.0.dist-info/RECORD
